{
  "cache_size": 8128755200,
  "results": [
    {
      "hit": 13236015,
      "iteration": 0,
      "metrics": [
        {
          "admission_treshold": 16,
          "algorithm": "lru",
          "hit": 461993,
          "inserted": 45711376,
          "layer": 0,
          "miss_ratio": 0.9899943839922098,
          "reinserted": 461993,
          "req": 46173369
        },
        {
          "admission_treshold": 16,
          "algorithm": "offline-clock",
          "hit": 12774022,
          "inserted": 5464915,
          "layer": 1,
          "miss_ratio": 0.7205504817881658,
          "reinserted": 6079024,
          "req": 45711376
        }
      ],
      "miss_ratio": 0.7133409303531653,
      "req": 46173369
    },
    {
      "hit": 13876568,
      "iteration": 1,
      "metrics": [
        {
          "admission_treshold": 16,
          "algorithm": "lru",
          "hit": 461993,
          "inserted": 45711376,
          "layer": 0,
          "miss_ratio": 0.9899943839922098,
          "reinserted": 461993,
          "req": 46173369
        },
        {
          "admission_treshold": 16,
          "algorithm": "offline-clock",
          "hit": 13414575,
          "inserted": 4822732,
          "layer": 1,
          "miss_ratio": 0.7065374929864285,
          "reinserted": 2301514,
          "req": 45711376
        }
      ],
      "miss_ratio": 0.6994681501364997,
      "req": 46173369
    }
  ],
  "trace": "w11.oracleGeneral.bin.zst"
}