{
  "cache_size": 4999,
  "results": [
    {
      "hit": 56980430,
      "iteration": 0,
      "metrics": [
        {
          "admission_treshold": 32,
          "algorithm": "lru",
          "hit": 17367110,
          "inserted": 82632890,
          "layer": 0,
          "miss_ratio": 0.8263289,
          "reinserted": 17367110,
          "req": 100000000
        },
        {
          "admission_treshold": 32,
          "algorithm": "offline-clock",
          "hit": 39613320,
          "inserted": 25815975,
          "layer": 1,
          "miss_ratio": 0.5206107398639936,
          "reinserted": 10031144,
          "req": 82632890
        }
      ],
      "miss_ratio": 0.43019569999999996,
      "req": 100000000
    },
    {
      "hit": 57285093,
      "iteration": 1,
      "metrics": [
        {
          "admission_treshold": 32,
          "algorithm": "lru",
          "hit": 17367110,
          "inserted": 82632890,
          "layer": 0,
          "miss_ratio": 0.8263289,
          "reinserted": 17367110,
          "req": 100000000
        },
        {
          "admission_treshold": 32,
          "algorithm": "offline-clock",
          "hit": 39917983,
          "inserted": 25508011,
          "layer": 1,
          "miss_ratio": 0.516923793903372,
          "reinserted": 5721986,
          "req": 82632890
        }
      ],
      "miss_ratio": 0.42714907,
      "req": 100000000
    }
  ],
  "trace": "zipf_1_5.oracleGeneral"
}